covidimpact.py
covidimpact-0.0.3.dist-info/METADATA
covidimpact-0.0.3.dist-info/WHEEL
covidimpact-0.0.3.dist-info/entry_points.txt
covidimpact-0.0.3.dist-info/top_level.txt
covidimpact-0.0.3.dist-info/RECORD
